{
  "data": {
    "ticker": "GKSL.NS",
    "fetch_date": "2026-03-15T10:34:29.800549",
    "quarterly_revenue": {
      "2024-12-31 00:00:00": 117893000.0,
      "2025-03-31 00:00:00": 895148000.0,
      "2025-06-30 00:00:00": 310900000.0,
      "2025-12-31 00:00:00": 232459000.0
    },
    "revenue_qoq_change": -25.23029913155355,
    "quarterly_eps": {
      "2024-12-31 00:00:00": 0.317618,
      "2025-03-31 00:00:00": NaN,
      "2025-06-30 00:00:00": 0.988823,
      "2025-12-31 00:00:00": 0.52
    },
    "eps_qoq_change": -47.41222645508852,
    "gross_margin": 86.87,
    "margin_change": -2.68,
    "operating_margin": 23.94,
    "quarterly_inventory": {
      "2025-03-31 00:00:00": 14467000.0,
      "2025-06-30 00:00:00": 13838000.0
    },
    "inventory_qoq_change": -4.35,
    "inventory_to_sales_ratio": 0.06,
    "inventory_breakdown_available": false
  },
  "fetched_at": "2026-03-15T10:34:29.802327"
}