{
  "data": {
    "ticker": "KICL.NS",
    "fetch_date": "2026-03-15T10:39:34.259954",
    "quarterly_revenue": {
      "2024-09-30 00:00:00": NaN,
      "2024-12-31 00:00:00": 0.0,
      "2025-03-31 00:00:00": 160490000.0,
      "2025-06-30 00:00:00": 0.0,
      "2025-09-30 00:00:00": 379870000.0,
      "2025-12-31 00:00:00": 25380000.0
    },
    "revenue_qoq_change": -93.31876694658699,
    "revenue_yoy_change": null,
    "quarterly_eps": {
      "2024-09-30 00:00:00": 88.13,
      "2024-12-31 00:00:00": 7.41,
      "2025-03-31 00:00:00": NaN,
      "2025-06-30 00:00:00": -7.29,
      "2025-09-30 00:00:00": 43.36,
      "2025-12-31 00:00:00": 3.92
    },
    "eps_qoq_change": -90.95940959409594,
    "eps_yoy_change": -47.09851551956815,
    "gross_margin": 91.53,
    "margin_change": -8.13,
    "operating_margin": -35.22,
    "inventory_breakdown_available": false
  },
  "fetched_at": "2026-03-15T10:39:34.261433"
}