{
  "data": {
    "ticker": "NITIRAJ.NS",
    "fetch_date": "2026-03-15T10:44:03.489956",
    "quarterly_revenue": {
      "2024-06-30 00:00:00": 42699000.0,
      "2024-09-30 00:00:00": 125591000.0,
      "2024-12-31 00:00:00": 370820000.0,
      "2025-03-31 00:00:00": 226062000.0,
      "2025-09-30 00:00:00": 163889000.0
    },
    "revenue_qoq_change": -27.502632021303892,
    "revenue_yoy_change": 283.82397714232184,
    "quarterly_eps": {
      "2024-06-30 00:00:00": -1.61,
      "2024-09-30 00:00:00": 0.02,
      "2024-12-31 00:00:00": 6.35,
      "2025-03-31 00:00:00": NaN,
      "2025-09-30 00:00:00": 1.59
    },
    "eps_qoq_change": null,
    "eps_yoy_change": 198.75776397515529,
    "gross_margin": 59.5,
    "margin_change": 35.11,
    "operating_margin": 11.01,
    "quarterly_inventory": {
      "2024-09-30 00:00:00": 211773000.0,
      "2025-03-31 00:00:00": 164309000.0,
      "2025-09-30 00:00:00": 207327000.0
    },
    "inventory_qoq_change": 26.18,
    "inventory_to_sales_ratio": 1.265,
    "inventory_breakdown_available": false
  },
  "fetched_at": "2026-03-15T10:44:03.491772"
}